odoo10_addon_crm_phone-10.0.1.0.0.99.dev11-py3.8-nspkg.pth
odoo/addons/crm_phone/__init__.py
odoo/addons/crm_phone/__manifest__.py
odoo/addons/crm_phone/demo/crm_phonecall.xml
odoo/addons/crm_phone/i18n/am.po
odoo/addons/crm_phone/i18n/bg.po
odoo/addons/crm_phone/i18n/ca.po
odoo/addons/crm_phone/i18n/crm_phone.pot
odoo/addons/crm_phone/i18n/de.po
odoo/addons/crm_phone/i18n/el_GR.po
odoo/addons/crm_phone/i18n/es.po
odoo/addons/crm_phone/i18n/es_ES.po
odoo/addons/crm_phone/i18n/fi.po
odoo/addons/crm_phone/i18n/fr.po
odoo/addons/crm_phone/i18n/gl.po
odoo/addons/crm_phone/i18n/it.po
odoo/addons/crm_phone/i18n/pt.po
odoo/addons/crm_phone/i18n/pt_BR.po
odoo/addons/crm_phone/i18n/pt_PT.po
odoo/addons/crm_phone/i18n/sl.po
odoo/addons/crm_phone/i18n/tr.po
odoo/addons/crm_phone/models/__init__.py
odoo/addons/crm_phone/models/crm_lead.py
odoo/addons/crm_phone/models/crm_phonecall.py
odoo/addons/crm_phone/models/phone_common.py
odoo/addons/crm_phone/models/res_partner.py
odoo/addons/crm_phone/models/res_users.py
odoo/addons/crm_phone/security/ir.model.access.csv
odoo/addons/crm_phone/security/phonecall_security.xml
odoo/addons/crm_phone/static/description/icon.png
odoo/addons/crm_phone/tests/__init__.py
odoo/addons/crm_phone/tests/test_crm_phone.py
odoo/addons/crm_phone/view/crm_lead.xml
odoo/addons/crm_phone/view/crm_phonecall.xml
odoo/addons/crm_phone/view/res_partner.xml
odoo/addons/crm_phone/view/res_users.xml
odoo/addons/crm_phone/wizard/__init__.py
odoo/addons/crm_phone/wizard/create_crm_phonecall.py
odoo/addons/crm_phone/wizard/create_crm_phonecall_view.xml
odoo/addons/crm_phone/wizard/number_not_found.py
odoo/addons/crm_phone/wizard/number_not_found_view.xml
odoo10_addon_crm_phone-10.0.1.0.0.99.dev11.dist-info/METADATA
odoo10_addon_crm_phone-10.0.1.0.0.99.dev11.dist-info/WHEEL
odoo10_addon_crm_phone-10.0.1.0.0.99.dev11.dist-info/namespace_packages.txt
odoo10_addon_crm_phone-10.0.1.0.0.99.dev11.dist-info/top_level.txt
odoo10_addon_crm_phone-10.0.1.0.0.99.dev11.dist-info/RECORD
